{
    "dependencies": "thermalfoundation",
	"populate": {
		"tar_pool": {
            "enabled": true,
			"distribution": "cave",
			"generator": {
				"type": "lake",
				"block": "metallurgy:molten_tar",
				"material": "midnight:nightstone",
				"use-material": false,
                "outline-block": "midnight:nightstone",
				"solid-outline": true
			},
			"cluster-count": 1,
			"chunk-chance": 5,
			"ground-level": 24,
			"biome": "all",
			"retrogen": true,
			"dimension": {
				"restriction": "whitelist",
				"value": [
					66
				]
			}
		},
        "water_pool": {
            "enabled": true,
			"distribution": "cave",
			"generator": {
				"type": "lake",
				"block": "minecraft:water",
				"material": "midnight:nightstone",
				"use-material": false,
                "outline-block": "midnight:nightstone",
				"solid-outline": true
			},
			"cluster-count": 1,
			"chunk-chance": 70,
			"ground-level": 60,
			"biome": "all",
			"retrogen": true,
			"dimension": {
				"restriction": "whitelist",
				"value": [
					66
				]
			}
		},
        "lava_pool": {
            "enabled": true,
			"distribution": "cave",
			"generator": {
				"type": "lake",
				"block": "minecraft:lava",
				"material": "midnight:nightstone",
				"use-material": false,
                "outline-block": "midnight:nightstone",
				"solid-outline": true
			},
			"cluster-count": 1,
			"chunk-chance": 50,
			"ground-level": 19,
			"biome": "all",
			"retrogen": true,
			"dimension": {
				"restriction": "whitelist",
				"value": [
					66
				]
			}
		}
	}
}